LICENSE.txt
README.md
setup.cfg
setup.py
BalancerPy.egg-info/PKG-INFO
BalancerPy.egg-info/SOURCES.txt
BalancerPy.egg-info/dependency_links.txt
BalancerPy.egg-info/not-zip-safe
BalancerPy.egg-info/requires.txt
BalancerPy.egg-info/top_level.txt
python/prod/__init__.py
python/prod/constants/balancer_constants.py
python/prod/cwpt/exchg/BalancerExchange.py
python/prod/cwpt/exchg/BalancerMath.py
python/prod/cwpt/exchg/__init__.py
python/prod/cwpt/exchg/balancer_constants.py
python/prod/cwpt/exchg/result/BalancerMathResult.py
python/prod/cwpt/exchg/result/__init__.py
python/prod/cwpt/factory/BalancerFactory.py
python/prod/cwpt/factory/__init__.py
python/prod/enums/Proc.py
python/prod/enums/__init__.py
python/prod/erc/ERC20.py
python/prod/erc/__init__.py
python/prod/process/join/Join.py
python/prod/process/join/__init__.py
python/prod/process/liquidity/AddLiquidity.py
python/prod/process/liquidity/RemoveLiquidity.py
python/prod/process/liquidity/__init__.py
python/prod/process/swap/Swap.py
python/prod/process/swap/__init__.py
python/prod/quote/CWPQuote.py
python/prod/quote/__init__.py
python/prod/utils/data/BalancerExchangeData.py
python/prod/utils/data/ExchangeData.py
python/prod/utils/data/FactoryData.py
python/prod/utils/data/__init__.py
python/prod/utils/interfaces/IExchange.py
python/prod/utils/interfaces/IExchangeFactory.py
python/prod/utils/interfaces/__init__.py
python/prod/vault/BalancerVault.py
python/prod/vault/__init__.py