Metadata-Version: 2.1
Name: BalancerPy
Version: 1.0.3
Summary: Balancer Analytics with Python
Home-page: https://github.com/defipy-devs/balancerpy
Author: icmoore
Author-email: defipy.devs@gmail.com
License: Apache-2.0
Classifier: License :: OSI Approved :: Apache Software License
Classifier: Programming Language :: Python :: 3
Classifier: Operating System :: OS Independent
Classifier: Intended Audience :: Developers
Classifier: Topic :: Software Development :: Libraries :: Python Modules
Classifier: Topic :: Scientific/Engineering :: Information Analysis
Classifier: Topic :: Internet :: WWW/HTTP :: Dynamic Content
License-File: LICENSE.txt
Requires-Dist: uniswappy>=1.7.3
